Workbook

Sheet Assumptions
A1: Quomate | Software Business P&L
A5: PRICING (per customer, AED)
A6: Tier | B6: Annual subscription | C6: One-time setup
A7: Small distributor | B7: 120000 | C7: 50000
A8: Mid distributor | B8: 200000 | C8: 90000
A9: Large group | B9: 320000 | C9: 140000
A11: Annual churn (of prior active base) | B11: 0.08
A13: NEW CUSTOMERS ADDED PER YEAR
A14: Tier | C14: Y1 | D14: Y2 | E14: Y3 | F14: Y4 | G14: Y5
A15: Small distributor | C15: 1 | D15: 4 | E15: 6 | F15: 5 | G15: 5
A16: Mid distributor | C16: 1 | D16: 3 | E16: 6 | F16: 5 | G16: 6
A17: Large group | C17: 1 | D17: 1 | E17: 2 | F17: 2 | G17: 2
A18: Total new / year | C18: =SUM(C15:C17) -> 3 | D18: =SUM(D15:D17) -> 8 | E18: =SUM(E15:E17) -> 14 | F18: =SUM(F15:F17) -> 12 | G18: =SUM(G15:G17) -> 13
A20: ACTIVE CUSTOMERS (end of year, after churn)
A21: Tier | C21: Y1 | D21: Y2 | E21: Y3 | F21: Y4 | G21: Y5
A22: Small distributor | C22: =C15 -> 1 | D22: =ROUND(C22*(1-$B$11),0)+D15 -> 5 | E22: =ROUND(D22*(1-$B$11),0)+E15 -> 11 | F22: =ROUND(E22*(1-$B$11),0)+F15 -> 15 | G22: =ROUND(F22*(1-$B$11),0)+G15 -> 19
A23: Mid distributor | C23: =C16 -> 1 | D23: =ROUND(C23*(1-$B$11),0)+D16 -> 4 | E23: =ROUND(D23*(1-$B$11),0)+E16 -> 10 | F23: =ROUND(E23*(1-$B$11),0)+F16 -> 14 | G23: =ROUND(F23*(1-$B$11),0)+G16 -> 19
A24: Large group | C24: =C17 -> 1 | D24: =ROUND(C24*(1-$B$11),0)+D17 -> 2 | E24: =ROUND(D24*(1-$B$11),0)+E17 -> 4 | F24: =ROUND(E24*(1-$B$11),0)+F17 -> 6 | G24: =ROUND(F24*(1-$B$11),0)+G17 -> 8
A25: Total active | C25: =SUM(C22:C24) -> 3 | D25: =SUM(D22:D24) -> 11 | E25: =SUM(E22:E24) -> 25 | F25: =SUM(F22:F24) -> 35 | G25: =SUM(G22:G24) -> 46
A27: COST & OPERATING ASSUMPTIONS
A28: Cost of revenue per active customer / yr | B28: 32000 | D28: AI/API inference, hosting, selection API, support??
A29: Onboarding delivery cost per new customer | B29: 18000 | D29: Catalogue load, ERP integration, training??
A30: One-time MVP build cost (Year 1) | B30: 400000
A32: Operating expenses per year (stepped)
A33: Founder draw (2 founders) | C33: 120000 | D33: 480000 | E33: 720000 | F33: 840000 | G33: 900000
A34: Engineering & product team | C34: 180000 | D34: 600000 | E34: 1100000 | F34: 1500000 | G34: 1900000
A35: Customer success & support | C35: 0 | D35: 120000 | E35: 300000 | F35: 480000 | G35: 620000
A36: Sales & marketing | C36: 60000 | D36: 220000 | E36: 450000 | F36: 620000 | G36: 780000
A37: Software, tools & infrastructure | C37: 40000 | D37: 90000 | E37: 150000 | F37: 200000 | G37: 250000
A38: Legal, admin, office, travel | C38: 50000 | D38: 110000 | E38: 180000 | F38: 240000 | G38: 300000
A40: Discount rate (for NPV) | B40: 0.2

Sheet P&L
A1: Quomate | Five-Year P&L (AED)
A2: All revenue and cost lines link to the Assumptions sheet. Black = formula, green = link.
A4: AED | C4: Year 1 | D4: Year 2 | E4: Year 3 | F4: Year 4 | G4: Year 5
A5: REVENUE
A6: Subscription revenue | C6: =Assumptions!$C$22*Assumptions!$B$7+Assumptions!$C$23*Assumptions!$B$8+Assumptions!$C$24*Assumptions!$B$9 -> 640000 | D6: =Assumptions!$D$22*Assumptions!$B$7+Assumptions!$D$23*Assumptions!$B$8+Assumptions!$D$24*Assumptions!$B$9 -> 2040000 | E6: =Assumptions!$E$22*Assumptions!$B$7+Assumptions!$E$23*Assumptions!$B$8+Assumptions!$E$24*Assumptions!$B$9 -> 4600000 | F6: =Assumptions!$F$22*Assumptions!$B$7+Assumptions!$F$23*Assumptions!$B$8+Assumptions!$F$24*Assumptions!$B$9 -> 6520000 | G6: =Assumptions!$G$22*Assumptions!$B$7+Assumptions!$G$23*Assumptions!$B$8+Assumptions!$G$24*Assumptions!$B$9 -> 8640000
A7: Setup / implementation revenue | C7: =Assumptions!$C$15*Assumptions!$C$7+Assumptions!$C$16*Assumptions!$C$8+Assumptions!$C$17*Assumptions!$C$9 -> 280000 | D7: =Assumptions!$D$15*Assumptions!$C$7+Assumptions!$D$16*Assumptions!$C$8+Assumptions!$D$17*Assumptions!$C$9 -> 610000 | E7: =Assumptions!$E$15*Assumptions!$C$7+Assumptions!$E$16*Assumptions!$C$8+Assumptions!$E$17*Assumptions!$C$9 -> 1120000 | F7: =Assumptions!$F$15*Assumptions!$C$7+Assumptions!$F$16*Assumptions!$C$8+Assumptions!$F$17*Assumptions!$C$9 -> 980000 | G7: =Assumptions!$G$15*Assumptions!$C$7+Assumptions!$G$16*Assumptions!$C$8+Assumptions!$G$17*Assumptions!$C$9 -> 1070000
A8: Total revenue | C8: =C6+C7 -> 920000 | D8: =D6+D7 -> 2650000 | E8: =E6+E7 -> 5720000 | F8: =F6+F7 -> 7500000 | G8: =G6+G7 -> 9710000
A10: COST OF REVENUE
A11: Hosting, inference & support | C11: =Assumptions!$C$25*Assumptions!$B$28 -> 96000 | D11: =Assumptions!$D$25*Assumptions!$B$28 -> 352000 | E11: =Assumptions!$E$25*Assumptions!$B$28 -> 800000 | F11: =Assumptions!$F$25*Assumptions!$B$28 -> 1120000 | G11: =Assumptions!$G$25*Assumptions!$B$28 -> 1472000
A12: Onboarding delivery | C12: =Assumptions!$C$18*Assumptions!$B$29 -> 54000 | D12: =Assumptions!$D$18*Assumptions!$B$29 -> 144000 | E12: =Assumptions!$E$18*Assumptions!$B$29 -> 252000 | F12: =Assumptions!$F$18*Assumptions!$B$29 -> 216000 | G12: =Assumptions!$G$18*Assumptions!$B$29 -> 234000
A13: Total cost of revenue | C13: =C11+C12 -> 150000 | D13: =D11+D12 -> 496000 | E13: =E11+E12 -> 1052000 | F13: =F11+F12 -> 1336000 | G13: =G11+G12 -> 1706000
A15: GROSS PROFIT | C15: =C8-C13 -> 770000 | D15: =D8-D13 -> 2154000 | E15: =E8-E13 -> 4668000 | F15: =F8-F13 -> 6164000 | G15: =G8-G13 -> 8004000
A16: Gross margin % | C16: =IF(C8=0,0,C15/C8) -> 0.83695652 | D16: =IF(D8=0,0,D15/D8) -> 0.81283019 | E16: =IF(E8=0,0,E15/E8) -> 0.81608392 | F16: =IF(F8=0,0,F15/F8) -> 0.82186667 | G16: =IF(G8=0,0,G15/G8) -> 0.82430484
A18: OPERATING EXPENSES
A19: Founder draw | C19: =Assumptions!$C$33 -> 120000 | D19: =Assumptions!$D$33 -> 480000 | E19: =Assumptions!$E$33 -> 720000 | F19: =Assumptions!$F$33 -> 840000 | G19: =Assumptions!$G$33 -> 900000
A20: Engineering & product | C20: =Assumptions!$C$34 -> 180000 | D20: =Assumptions!$D$34 -> 600000 | E20: =Assumptions!$E$34 -> 1100000 | F20: =Assumptions!$F$34 -> 1500000 | G20: =Assumptions!$G$34 -> 1900000
A21: Customer success & support | C21: =Assumptions!$C$35 -> 0 | D21: =Assumptions!$D$35 -> 120000 | E21: =Assumptions!$E$35 -> 300000 | F21: =Assumptions!$F$35 -> 480000 | G21: =Assumptions!$G$35 -> 620000
A22: Sales & marketing | C22: =Assumptions!$C$36 -> 60000 | D22: =Assumptions!$D$36 -> 220000 | E22: =Assumptions!$E$36 -> 450000 | F22: =Assumptions!$F$36 -> 620000 | G22: =Assumptions!$G$36 -> 780000
A23: Software, tools & infrastructure | C23: =Assumptions!$C$37 -> 40000 | D23: =Assumptions!$D$37 -> 90000 | E23: =Assumptions!$E$37 -> 150000 | F23: =Assumptions!$F$37 -> 200000 | G23: =Assumptions!$G$37 -> 250000
A24: Legal, admin, office, travel | C24: =Assumptions!$C$38 -> 50000 | D24: =Assumptions!$D$38 -> 110000 | E24: =Assumptions!$E$38 -> 180000 | F24: =Assumptions!$F$38 -> 240000 | G24: =Assumptions!$G$38 -> 300000
A25: Total operating expenses | C25: =SUM(C19:C24) -> 450000 | D25: =SUM(D19:D24) -> 1620000 | E25: =SUM(E19:E24) -> 2900000 | F25: =SUM(F19:F24) -> 3880000 | G25: =SUM(G19:G24) -> 4750000
A27: Operating profit (before build cost) | C27: =C15-C25 -> 320000 | D27: =D15-D25 -> 534000 | E27: =E15-E25 -> 1768000 | F27: =F15-F25 -> 2284000 | G27: =G15-G25 -> 3254000
A28: One-time MVP build cost | C28: =Assumptions!$B$30 -> 400000 | D28: 0 | E28: 0 | F28: 0 | G28: 0
A29: NET PROFIT (pre-tax) | C29: =C27-C28 -> -80000 | D29: =D27-D28 -> 534000 | E29: =E27-E28 -> 1768000 | F29: =F27-F28 -> 2284000 | G29: =G27-G28 -> 3254000
A30: Net margin % | C30: =IF(C8=0,0,C29/C8) -> -0.086956522 | D30: =IF(D8=0,0,D29/D8) -> 0.20150943 | E30: =IF(E8=0,0,E29/E8) -> 0.30909091 | F30: =IF(F8=0,0,F29/F8) -> 0.30453333 | G30: =IF(G8=0,0,G29/G8) -> 0.33511843
A32: Cumulative net profit | C32: =C29 -> -80000 | D32: =C32+D29 -> 454000 | E32: =D32+E29 -> 2222000 | F32: =E32+F29 -> 4506000 | G32: =F32+G29 -> 7760000
A34: KEY METRICS
A35: Active customers (EOY) | C35: =Assumptions!$C$25 -> 3 | D35: =Assumptions!$D$25 -> 11 | E35: =Assumptions!$E$25 -> 25 | F35: =Assumptions!$F$25 -> 35 | G35: =Assumptions!$G$25 -> 46
A36: Revenue per active customer | C36: =IF(C35=0,0,C8/C35) -> 306666.67 | D36: =IF(D35=0,0,D8/D35) -> 240909.09 | E36: =IF(E35=0,0,E8/E35) -> 228800 | F36: =IF(F35=0,0,F8/F35) -> 214285.71 | G36: =IF(G35=0,0,G8/G35) -> 211086.96
A38: 5-year NPV of net profit | C38: =NPV(Assumptions!$B$40,C29:G29) -> 3736490.5
A39: Cumulative net profit, Year 5 | C39: =G32 -> 7760000
A43: VALUATION VIEW (illustrative, not a forecast)
A47: Year 5 ARR (recurring subscription only) | C47: =G6 -> 8640000
A49: ARR multiple | C49: Enterprise value (AED)
A50: Conservative | B50: 4 | C50: =$C$47*B50 -> 34560000
A51: Base | B51: 6 | C51: =$C$47*B51 -> 51840000
A52: Optimistic | B52: 8 | C52: =$C$47*B52 -> 69120000
A53: Bull | B53: 10 | C53: =$C$47*B53 -> 86400000
